Workbook

Sheet Scoring Model
A1: Fit and proper risk scoring model — 15 question subset
A2: Risk score: lower is better. Yellow cells are inputs; grey cells are calculated. Generated from the applicant JSON, so weights, polarity, knockout flags and question text match the engine input. Pre-filled with APP001's answers.
A4: Section | B4: Section weight | C4: QID | D4: Question | E4: Polarity | F4: Question weight | G4: Answer (Yes/No/N/A) | H4: Risk flag | I4: Applicable weight | J4: Weighted risk | K4: Knockout | L4: Basis for the weight
A5: Basic Details | B5: 4 | C5: A1 | D5: Is the applicant between 45–60 years of age? | E5: Positive | F5: 2.5 | G5: Yes | H5: =IF(G5="N/A",0,IF(E5="Positive",IF(G5="Yes",0,1),IF(G5="Yes",1,0))) -> 0 | I5: =IF(G5="N/A",0,F5) -> 2.5 | J5: =H5*I5 -> 0 | K5: 0 | L5: Age band is a weak signal on its own; carries the least weight of any criterion.
A6: Basic Details | B6: 4 | C6: A4 | D6: Is the applicant a naturalized citizen? | E6: Negative | F6: 1.5 | G6: No | H6: =IF(G6="N/A",0,IF(E6="Positive",IF(G6="Yes",0,1),IF(G6="Yes",1,0))) -> 0 | I6: =IF(G6="N/A",0,F6) -> 1.5 | J6: =H6*I6 -> 0 | K6: 0 | L6: Revised to Negative: a Yes (naturalised) contributes the full weight. Lowest weight in the model; the route to citizenship is administrative rather than a conduct finding.
A7: Qualifications & Experience | B7: 18 | C7: Q1 | D7: Does the applicant hold a relevant academic qualification? | E7: Positive | F7: 6 | G7: Yes | H7: =IF(G7="N/A",0,IF(E7="Positive",IF(G7="Yes",0,1),IF(G7="Yes",1,0))) -> 0 | I7: =IF(G7="N/A",0,F7) -> 6 | J7: =H7*I7 -> 0 | K7: 0 | L7: A qualification is a threshold requirement but a weak predictor once experience is known.
A8: Qualifications & Experience | B8: 18 | C8: Q3 | D8: Does the applicant have ≥10 years relevant experience? | E8: Positive | F8: 12 | G8: Yes | H8: =IF(G8="N/A",0,IF(E8="Positive",IF(G8="Yes",0,1),IF(G8="Yes",1,0))) -> 0 | I8: =IF(G8="N/A",0,F8) -> 12 | J8: =H8*I8 -> 0 | K8: 0 | L8: Depth of relevant experience is the strongest competence signal available; weighted twice the qualification.
A9: Professional Conduct /Reputation/Integrity | B9: 26 | C9: PC1 | D9: Have you at any time been charged with or convicted of any offence or otherwise found liable by a Civil, Criminal or Military Court (excluding minor road traffic offences), in any jurisdiction? | E9: Negative | F9: 18 | G9: No | H9: =IF(G9="N/A",0,IF(E9="Positive",IF(G9="Yes",0,1),IF(G9="Yes",1,0))) -> 0 | I9: =IF(G9="N/A",0,F9) -> 18 | J9: =H9*I9 -> 0 | K9: 1 | L9: Conviction or civil liability goes to integrity. Heaviest single weight and a knock-out: a Yes refers the case regardless of total score.
A10: Professional Conduct /Reputation/Integrity | B10: 26 | C10: PC19 | D10: Was there a time when you were not in compliance with any tax or other statutory requirements imposed on you? (Section 3(1)(iii) of the Act) | E10: Negative | F10: 8 | G10: No | H10: =IF(G10="N/A",0,IF(E10="Positive",IF(G10="Yes",0,1),IF(G10="Yes",1,0))) -> 0 | I10: =IF(G10="N/A",0,F10) -> 8 | J10: =H10*I10 -> 0 | K10: 0 | L10: Tax or statutory non-compliance is material but often historic and remediable; weighted well below a conviction.
A11: Financial Soundness | B11: 16 | C11: FC5 | D11: Has any loan or credit facility (or part thereof) extended to you by any financial institution, been restructured, renegotiated, provided against or been the subject of a write-off or debt forgiveness for reasons of non-payment by you? | E11: Negative | F11: 10 | G11: No | H11: =IF(G11="N/A",0,IF(E11="Positive",IF(G11="Yes",0,1),IF(G11="Yes",1,0))) -> 0 | I11: =IF(G11="N/A",0,F11) -> 10 | J11: =H11*I11 -> 0 | K11: 0 | L11: A restructured or written-off facility evidences realised default, not just exposure. Heavier than gross indebtedness.
A12: Financial Soundness | B12: 16 | C12: FC7 | D12: Do you (in your personal capacity), or through any legal person or arrangement controlled by you and/or any immediate relative have outstanding any loans or other forms of indebtedness (including guarantees) in excess of N$2.5mn? | E12: Negative | F12: 6 | G12: No | H12: =IF(G12="N/A",0,IF(E12="Positive",IF(G12="Yes",0,1),IF(G12="Yes",1,0))) -> 0 | I12: =IF(G12="N/A",0,F12) -> 6 | J12: =H12*I12 -> 0 | K12: 0 | L12: Indebtedness above the threshold is a scale measure; serviced debt is not itself misconduct.
A13: Conflict of interest. (Entity/Enterprise based) | B13: 14 | C13: CoI2 | D13: Have you ever been or are you currently a Director of any limited liability companies, societies, or other business enterprises engaged in financial services, as defined in the BSA? | E13: Negative | F13: 5 | G13: Yes | H13: =IF(G13="N/A",0,IF(E13="Positive",IF(G13="Yes",0,1),IF(G13="Yes",1,0))) -> 1 | I13: =IF(G13="N/A",0,F13) -> 5 | J13: =H13*I13 -> 5 | K13: 0 | L13: A directorship elsewhere in financial services is disclosable and common; low weight unless it becomes a control position.
A14: Conflict of interest. (Entity/Enterprise based) | B14: 14 | C14: CoI6 | D14: Are you a beneficial owner of a controlling interest (20% or more of the voting shares, or the ability to appoint or remove a majority of the board) in any financial institution, partnerships, societies, or trust corporations or other body, organization or entity whether for business, benevolent or other purposes? | E14: Negative | F14: 9 | G14: No | H14: =IF(G14="N/A",0,IF(E14="Positive",IF(G14="Yes",0,1),IF(G14="Yes",1,0))) -> 0 | I14: =IF(G14="N/A",0,F14) -> 9 | J14: =H14*I14 -> 0 | K14: 0 | L14: Beneficial ownership of a controlling interest creates a durable conflict the licensee cannot manage away; weighted above a plain directorship.
A15: Time Commitment | B15: 8 | C15: T1 | D15: Will you be actively engaged in the business of the Licensee to which this application relates and devote the major portion of your time thereto? | E15: Positive | F15: 5 | G15: No | H15: =IF(G15="N/A",0,IF(E15="Positive",IF(G15="Yes",0,1),IF(G15="Yes",1,0))) -> 1 | I15: =IF(G15="N/A",0,F15) -> 5 | J15: =H15*I15 -> 5 | K15: 0 | L15: Insufficient time commitment is a live governance risk for an executive appointment. For a non-executive the expected answer is No, which this polarity charges — treatment open, see Notes and Worked Examples.
A16: Time Commitment | B16: 8 | C16: T2 | D16: If you are completing this form in the capacity of director or proposed director, please indicate whether you have or will have any executive responsibility for the management of the institution’s business | E16: Positive | F16: 3 | G16: N/A | H16: =IF(G16="N/A",0,IF(E16="Positive",IF(G16="Yes",0,1),IF(G16="Yes",1,0))) -> 0 | I16: =IF(G16="N/A",0,F16) -> 0 | J16: =H16*I16 -> 0 | K16: 0 | L16: Set to N/A for a non-executive appointment, where an answer of No is expected and carries no risk.
... A19: Collective Suitability | B19: 6 | C19: CS4 | D19: Have you acquainted yourself with and do you understand the extent of the rights and powers, as well as your responsibilities and duties, as a director, officer or key employee or a proposed director, officer or key employee of the institution for which this questionnaire is being completed, as contained in the applicable law, regulations, and guidelines? | E19: Positive | F19: 6 | G19: Yes | H19: =IF(G19="N/A",0,IF(E19="Positive",IF(G19="Yes",0,1),IF(G19="Yes",1,0))) -> 0 | I19: =IF(G19="N/A",0,F19) -> 6 | J19: =H19*I19 -> 0 | K19: 0 | L19: An attestation of understanding of duties. Failing it is serious, but it is self-declared and easily remedied.
D20: Total | F20: =SUM(F5:F19) -> 100 | I20: =SUM(I5:I19) -> 97 | J20: =SUM(J5:J19) -> 10
A22: Assessment outcome
A23: Total applicable weight | B23: =I20 -> 97 | C23: Sum of weights for questions that apply (N/A excluded)
A24: Total weighted risk | B24: =J20 -> 10 | C24: Sum of weight × risk flag
A25: Normalised risk score (0–1) | B25: =IFERROR(B24/B23,0) -> 0.10309278 | C25: Weighted risk divided by applicable weight
A26: Risk score (0–100) | B26: =B25*100 -> 10.309278 | C26: The same figure on a 100 point scale
A27: Risk band | B27: =INDEX(Bands!$B$4:$B$7,MATCH(B25,Bands!$A$4:$A$7,1)) -> Moderate | C27: From the Bands sheet
A28: Knockout triggered | B28: =IF(SUMPRODUCT((K5:K19=1)*(H5:H19=1))>0,"Yes","No") -> No | C28: A risk flag on any knockout question overrides the band
A29: Recommendation | B29: =IF(B28="Yes","Refer to committee — knockout criterion met",INDEX(Bands!$C$4:$C$7,MATCH(B25,Bands!$A$4:$A$7,1))) -> Approve with conditions or monitoring

Sheet Bands
A1: Risk bands and knockout rules
A2: Lower score is better. Thresholds are lower bounds; MATCH finds the highest bound not exceeding the score.
A3: Lower bound | B3: Band | C3: Recommended action
A4: 0 | B4: Low | C4: Recommend approval
A5: 0.1 | B5: Moderate | C5: Approve with conditions or monitoring
A6: 0.25 | B6: Elevated | C6: Refer for supervisory review
A7: 0.45 | B7: High | C7: Recommend rejection
A9: Knockout criteria
A10: PC1 risk flag = 1 | B10: Conviction or civil liability found by a court. The case is referred regardless of the weighted score.
A11: Scoring precondition | B11: Scoring runs only on a fully authenticated submission. Any mismatch, missing document or unverifiable field is resolved with the filer before the scoring engine is called, so the engine only ever sees corrected answers.

Sheet Section Weights
A1: Section weights and the split within each section
A2: Section weights sum to 100. Within a section, question weights sum to the section weight.
A3: Section | B3: Section weight | C3: Questions | D3: Split | E3: Why this weight
A4: Basic Details | B4: 4 | C4: A1, A4 | D4: A1 = 2.5 / A4 = 1.5 | E4: Demographic proxy only. Deliberately the smallest weight; it is in the model because the source questionnaire has it.
A5: Qualifications & Experience | B5: 18 | C5: Q1, Q3 | D5: Q1 = 6 / Q3 = 12 | E5: Competence. Second heaviest, driven almost entirely by depth of relevant experience.
A6: Professional Conduct /Reputation/Integrity | B6: 26 | C6: PC1, PC19 | D6: PC1 = 18 / PC19 = 8 | E6: Integrity. Heaviest section and the only one carrying a knock-out, since honesty and record are the core of a fit and proper test.
A7: Financial Soundness | B7: 16 | C7: FC5, FC7 | D7: FC5 = 10 / FC7 = 6 | E7: Personal financial distress is a recognised driver of misconduct risk and of susceptibility to influence.
A8: Conflict of interest. (Entity/Enterprise based) | B8: 14 | C8: CoI2, CoI6 | D8: CoI2 = 5 / CoI6 = 9 | E8: External positions and ownership that compete with the licensee's interests.
A9: Time Commitment | B9: 8 | C9: T1, T2 | D9: T1 = 5 / T2 = 3 | E9: Governance capacity. Material for executives, largely inapplicable for non-executives.
A10: Conflict of interest. (Licensee based) | B10: 8 | C10: CoL1, CoL3 | D10: CoL1 = 5 / CoL3 = 3 | E10: Holdings in the licensee itself. Disclosable and manageable, so weighted below external conflicts.
A11: Collective Suitability | B11: 6 | C11: CS4 | D11: CS4 = 6 | E11: Self-attested understanding of duties. Low weight because it is self-declared.
A12: Total | B12: =SUM(B4:B11) -> 100
A13: Check: question weights sum to section weight | B13: =IF(ROUND(SUM('Scoring Model'!F5:F19)-B12,6)=0,"OK","MISMATCH") -> OK

Sheet Worked Examples
A1: The five test applicants scored against this model
A2: Answers are those that reach the scoring engine: as submitted, except the three answers authentication corrects first (highlighted, listed below). Weights and polarity are read from the Scoring Model sheet.
A4: QID | B4: Question weight | C4: APP001 Johanna N. Amutenya | D4: APP002 Petrus K. Shivute | E4: APP003 Elias T. Haufiku | F4: APP004 Maria L. van Wyk | G4: APP005 Margaret Kaapanda | H4: APP001 risk | I4: APP002 risk | J4: APP003 risk | K4: APP004 risk | L4: APP005 risk | M4: APP001 applicable | N4: APP002 applicable | O4: APP003 applicable | P4: APP004 applicable | Q4: APP005 applicable
A5: A1 | B5: ='Scoring Model'!F5 -> 2.5 | C5: Yes | D5: No | E5: Yes | F5: Yes | G5: No | H5: =IF(C5="N/A",0,IF('Scoring Model'!$E5="Positive",IF(C5="Yes",0,1),IF(C5="Yes",1,0)))*IF(C5="N/A",0,'Scoring Model'!$F5) -> 0 | I5: =IF(D5="N/A",0,IF('Scoring Model'!$E5="Positive",IF(D5="Yes",0,1),IF(D5="Yes",1,0)))*IF(D5="N/A",0,'Scoring Model'!$F5) -> 2.5 | J5: =IF(E5="N/A",0,IF('Scoring Model'!$E5="Positive",IF(E5="Yes",0,1),IF(E5="Yes",1,0)))*IF(E5="N/A",0,'Scoring Model'!$F5) -> 0 | K5: =IF(F5="N/A",0,IF('Scoring Model'!$E5="Positive",IF(F5="Yes",0,1),IF(F5="Yes",1,0)))*IF(F5="N/A",0,'Scoring Model'!$F5) -> 0 | L5: =IF(G5="N/A",0,IF('Scoring Model'!$E5="Positive",IF(G5="Yes",0,1),IF(G5="Yes",1,0)))*IF(G5="N/A",0,'Scoring Model'!$F5) -> 2.5 | M5: =IF(C5="N/A",0,'Scoring Model'!$F5) -> 2.5 | N5: =IF(D5="N/A",0,'Scoring Model'!$F5) -> 2.5 | O5: =IF(E5="N/A",0,'Scoring Model'!$F5) -> 2.5 | P5: =IF(F5="N/A",0,'Scoring Model'!$F5) -> 2.5 | Q5: =IF(G5="N/A",0,'Scoring Model'!$F5) -> 2.5
A6: A4 | B6: ='Scoring Model'!F6 -> 1.5 | C6: No | D6: No | E6: Yes | F6: No | G6: No | H6: =IF(C6="N/A",0,IF('Scoring Model'!$E6="Positive",IF(C6="Yes",0,1),IF(C6="Yes",1,0)))*IF(C6="N/A",0,'Scoring Model'!$F6) -> 0 | I6: =IF(D6="N/A",0,IF('Scoring Model'!$E6="Positive",IF(D6="Yes",0,1),IF(D6="Yes",1,0)))*IF(D6="N/A",0,'Scoring Model'!$F6) -> 0 | J6: =IF(E6="N/A",0,IF('Scoring Model'!$E6="Positive",IF(E6="Yes",0,1),IF(E6="Yes",1,0)))*IF(E6="N/A",0,'Scoring Model'!$F6) -> 1.5 | K6: =IF(F6="N/A",0,IF('Scoring Model'!$E6="Positive",IF(F6="Yes",0,1),IF(F6="Yes",1,0)))*IF(F6="N/A",0,'Scoring Model'!$F6) -> 0 | L6: =IF(G6="N/A",0,IF('Scoring Model'!$E6="Positive",IF(G6="Yes",0,1),IF(G6="Yes",1,0)))*IF(G6="N/A",0,'Scoring Model'!$F6) -> 0 | M6: =IF(C6="N/A",0,'Scoring Model'!$F6) -> 1.5 | N6: =IF(D6="N/A",0,'Scoring Model'!$F6) -> 1.5 | O6: =IF(E6="N/A",0,'Scoring Model'!$F6) -> 1.5 | P6: =IF(F6="N/A",0,'Scoring Model'!$F6) -> 1.5 | Q6: =IF(G6="N/A",0,'Scoring Model'!$F6) -> 1.5
A7: Q1 | B7: ='Scoring Model'!F7 -> 6 | C7: Yes | D7: Yes | E7: Yes | F7: Yes | G7: Yes | H7: =IF(C7="N/A",0,IF('Scoring Model'!$E7="Positive",IF(C7="Yes",0,1),IF(C7="Yes",1,0)))*IF(C7="N/A",0,'Scoring Model'!$F7) -> 0 | I7: =IF(D7="N/A",0,IF('Scoring Model'!$E7="Positive",IF(D7="Yes",0,1),IF(D7="Yes",1,0)))*IF(D7="N/A",0,'Scoring Model'!$F7) -> 0 | J7: =IF(E7="N/A",0,IF('Scoring Model'!$E7="Positive",IF(E7="Yes",0,1),IF(E7="Yes",1,0)))*IF(E7="N/A",0,'Scoring Model'!$F7) -> 0 | K7: =IF(F7="N/A",0,IF('Scoring Model'!$E7="Positive",IF(F7="Yes",0,1),IF(F7="Yes",1,0)))*IF(F7="N/A",0,'Scoring Model'!$F7) -> 0 | L7: =IF(G7="N/A",0,IF('Scoring Model'!$E7="Positive",IF(G7="Yes",0,1),IF(G7="Yes",1,0)))*IF(G7="N/A",0,'Scoring Model'!$F7) -> 0 | M7: =IF(C7="N/A",0,'Scoring Model'!$F7) -> 6 | N7: =IF(D7="N/A",0,'Scoring Model'!$F7) -> 6 | O7: =IF(E7="N/A",0,'Scoring Model'!$F7) -> 6 | P7: =IF(F7="N/A",0,'Scoring Model'!$F7) -> 6 | Q7: =IF(G7="N/A",0,'Scoring Model'!$F7) -> 6
A8: Q3 | B8: ='Scoring Model'!F8 -> 12 | C8: Yes | D8: Yes | E8: No | F8: Yes | G8: Yes | H8: =IF(C8="N/A",0,IF('Scoring Model'!$E8="Positive",IF(C8="Yes",0,1),IF(C8="Yes",1,0)))*IF(C8="N/A",0,'Scoring Model'!$F8) -> 0 | I8: =IF(D8="N/A",0,IF('Scoring Model'!$E8="Positive",IF(D8="Yes",0,1),IF(D8="Yes",1,0)))*IF(D8="N/A",0,'Scoring Model'!$F8) -> 0 | J8: =IF(E8="N/A",0,IF('Scoring Model'!$E8="Positive",IF(E8="Yes",0,1),IF(E8="Yes",1,0)))*IF(E8="N/A",0,'Scoring Model'!$F8) -> 12 | K8: =IF(F8="N/A",0,IF('Scoring Model'!$E8="Positive",IF(F8="Yes",0,1),IF(F8="Yes",1,0)))*IF(F8="N/A",0,'Scoring Model'!$F8) -> 0 | L8: =IF(G8="N/A",0,IF('Scoring Model'!$E8="Positive",IF(G8="Yes",0,1),IF(G8="Yes",1,0)))*IF(G8="N/A",0,'Scoring Model'!$F8) -> 0 | M8: =IF(C8="N/A",0,'Scoring Model'!$F8) -> 12 | N8: =IF(D8="N/A",0,'Scoring Model'!$F8) -> 12 | O8: =IF(E8="N/A",0,'Scoring Model'!$F8) -> 12 | P8: =IF(F8="N/A",0,'Scoring Model'!$F8) -> 12 | Q8: =IF(G8="N/A",0,'Scoring Model'!$F8) -> 12
A9: PC1 | B9: ='Scoring Model'!F9 -> 18 | C9: No | D9: No | E9: No | F9: Yes | G9: No | H9: =IF(C9="N/A",0,IF('Scoring Model'!$E9="Positive",IF(C9="Yes",0,1),IF(C9="Yes",1,0)))*IF(C9="N/A",0,'Scoring Model'!$F9) -> 0 | I9: =IF(D9="N/A",0,IF('Scoring Model'!$E9="Positive",IF(D9="Yes",0,1),IF(D9="Yes",1,0)))*IF(D9="N/A",0,'Scoring Model'!$F9) -> 0 | J9: =IF(E9="N/A",0,IF('Scoring Model'!$E9="Positive",IF(E9="Yes",0,1),IF(E9="Yes",1,0)))*IF(E9="N/A",0,'Scoring Model'!$F9) -> 0 | K9: =IF(F9="N/A",0,IF('Scoring Model'!$E9="Positive",IF(F9="Yes",0,1),IF(F9="Yes",1,0)))*IF(F9="N/A",0,'Scoring Model'!$F9) -> 18 | L9: =IF(G9="N/A",0,IF('Scoring Model'!$E9="Positive",IF(G9="Yes",0,1),IF(G9="Yes",1,0)))*IF(G9="N/A",0,'Scoring Model'!$F9) -> 0 | M9: =IF(C9="N/A",0,'Scoring Model'!$F9) -> 18 | N9: =IF(D9="N/A",0,'Scoring Model'!$F9) -> 18 | O9: =IF(E9="N/A",0,'Scoring Model'!$F9) -> 18 | P9: =IF(F9="N/A",0,'Scoring Model'!$F9) -> 18 | Q9: =IF(G9="N/A",0,'Scoring Model'!$F9) -> 18
A10: PC19 | B10: ='Scoring Model'!F10 -> 8 | C10: No | D10: No | E10: Yes | F10: No | G10: No | H10: =IF(C10="N/A",0,IF('Scoring Model'!$E10="Positive",IF(C10="Yes",0,1),IF(C10="Yes",1,0)))*IF(C10="N/A",0,'Scoring Model'!$F10) -> 0 | I10: =IF(D10="N/A",0,IF('Scoring Model'!$E10="Positive",IF(D10="Yes",0,1),IF(D10="Yes",1,0)))*IF(D10="N/A",0,'Scoring Model'!$F10) -> 0 | J10: =IF(E10="N/A",0,IF('Scoring Model'!$E10="Positive",IF(E10="Yes",0,1),IF(E10="Yes",1,0)))*IF(E10="N/A",0,'Scoring Model'!$F10) -> 8 | K10: =IF(F10="N/A",0,IF('Scoring Model'!$E10="Positive",IF(F10="Yes",0,1),IF(F10="Yes",1,0)))*IF(F10="N/A",0,'Scoring Model'!$F10) -> 0 | L10: =IF(G10="N/A",0,IF('Scoring Model'!$E10="Positive",IF(G10="Yes",0,1),IF(G10="Yes",1,0)))*IF(G10="N/A",0,'Scoring Model'!$F10) -> 0 | M10: =IF(C10="N/A",0,'Scoring Model'!$F10) -> 8 | N10: =IF(D10="N/A",0,'Scoring Model'!$F10) -> 8 | O10: =IF(E10="N/A",0,'Scoring Model'!$F10) -> 8 | P10: =IF(F10="N/A",0,'Scoring Model'!$F10) -> 8 | Q10: =IF(G10="N/A",0,'Scoring Model'!$F10) -> 8
A11: FC5 | B11: ='Scoring Model'!F11 -> 10 | C11: No | D11: No | E11: No | F11: Yes | G11: No | H11: =IF(C11="N/A",0,IF('Scoring Model'!$E11="Positive",IF(C11="Yes",0,1),IF(C11="Yes",1,0)))*IF(C11="N/A",0,'Scoring Model'!$F11) -> 0 | I11: =IF(D11="N/A",0,IF('Scoring Model'!$E11="Positive",IF(D11="Yes",0,1),IF(D11="Yes",1,0)))*IF(D11="N/A",0,'Scoring Model'!$F11) -> 0 | J11: =IF(E11="N/A",0,IF('Scoring Model'!$E11="Positive",IF(E11="Yes",0,1),IF(E11="Yes",1,0)))*IF(E11="N/A",0,'Scoring Model'!$F11) -> 0 | K11: =IF(F11="N/A",0,IF('Scoring Model'!$E11="Positive",IF(F11="Yes",0,1),IF(F11="Yes",1,0)))*IF(F11="N/A",0,'Scoring Model'!$F11) -> 10 | L11: =IF(G11="N/A",0,IF('Scoring Model'!$E11="Positive",IF(G11="Yes",0,1),IF(G11="Yes",1,0)))*IF(G11="N/A",0,'Scoring Model'!$F11) -> 0 | M11: =IF(C11="N/A",0,'Scoring Model'!$F11) -> 10 | N11: =IF(D11="N/A",0,'Scoring Model'!$F11) -> 10 | O11: =IF(E11="N/A",0,'Scoring Model'!$F11) -> 10 | P11: =IF(F11="N/A",0,'Scoring Model'!$F11) -> 10 | Q11: =IF(G11="N/A",0,'Scoring Model'!$F11) -> 10
A12: FC7 | B12: ='Scoring Model'!F12 -> 6 | C12: No | D12: No | E12: No | F12: Yes | G12: No | H12: =IF(C12="N/A",0,IF('Scoring Model'!$E12="Positive",IF(C12="Yes",0,1),IF(C12="Yes",1,0)))*IF(C12="N/A",0,'Scoring Model'!$F12) -> 0 | I12: =IF(D12="N/A",0,IF('Scoring Model'!$E12="Positive",IF(D12="Yes",0,1),IF(D12="Yes",1,0)))*IF(D12="N/A",0,'Scoring Model'!$F12) -> 0 | J12: =IF(E12="N/A",0,IF('Scoring Model'!$E12="Positive",IF(E12="Yes",0,1),IF(E12="Yes",1,0)))*IF(E12="N/A",0,'Scoring Model'!$F12) -> 0 | K12: =IF(F12="N/A",0,IF('Scoring Model'!$E12="Positive",IF(F12="Yes",0,1),IF(F12="Yes",1,0)))*IF(F12="N/A",0,'Scoring Model'!$F12) -> 6 | L12: =IF(G12="N/A",0,IF('Scoring Model'!$E12="Positive",IF(G12="Yes",0,1),IF(G12="Yes",1,0)))*IF(G12="N/A",0,'Scoring Model'!$F12) -> 0 | M12: =IF(C12="N/A",0,'Scoring Model'!$F12) -> 6 | N12: =IF(D12="N/A",0,'Scoring Model'!$F12) -> 6 | O12: =IF(E12="N/A",0,'Scoring Model'!$F12) -> 6 | P12: =IF(F12="N/A",0,'Scoring Model'!$F12) -> 6 | Q12: =IF(G12="N/A",0,'Scoring Model'!$F12) -> 6
A13: CoI2 | B13: ='Scoring Model'!F13 -> 5 | C13: Yes | D13: Yes | E13: Yes | F13: Yes | G13: Yes | H13: =IF(C13="N/A",0,IF('Scoring Model'!$E13="Positive",IF(C13="Yes",0,1),IF(C13="Yes",1,0)))*IF(C13="N/A",0,'Scoring Model'!$F13) -> 5 | I13: =IF(D13="N/A",0,IF('Scoring Model'!$E13="Positive",IF(D13="Yes",0,1),IF(D13="Yes",1,0)))*IF(D13="N/A",0,'Scoring Model'!$F13) -> 5 | J13: =IF(E13="N/A",0,IF('Scoring Model'!$E13="Positive",IF(E13="Yes",0,1),IF(E13="Yes",1,0)))*IF(E13="N/A",0,'Scoring Model'!$F13) -> 5 | K13: =IF(F13="N/A",0,IF('Scoring Model'!$E13="Positive",IF(F13="Yes",0,1),IF(F13="Yes",1,0)))*IF(F13="N/A",0,'Scoring Model'!$F13) -> 5 | L13: =IF(G13="N/A",0,IF('Scoring Model'!$E13="Positive",IF(G13="Yes",0,1),IF(G13="Yes",1,0)))*IF(G13="N/A",0,'Scoring Model'!$F13) -> 5 | M13: =IF(C13="N/A",0,'Scoring Model'!$F13) -> 5 | N13: =IF(D13="N/A",0,'Scoring Model'!$F13) -> 5 | O13: =IF(E13="N/A",0,'Scoring Model'!$F13) -> 5 | P13: =IF(F13="N/A",0,'Scoring Model'!$F13) -> 5 | Q13: =IF(G13="N/A",0,'Scoring Model'!$F13) -> 5
A14: CoI6 | B14: ='Scoring Model'!F14 -> 9 | C14: No | D14: No | E14: No | F14: Yes | G14: No | H14: =IF(C14="N/A",0,IF('Scoring Model'!$E14="Positive",IF(C14="Yes",0,1),IF(C14="Yes",1,0)))*IF(C14="N/A",0,'Scoring Model'!$F14) -> 0 | I14: =IF(D14="N/A",0,IF('Scoring Model'!$E14="Positive",IF(D14="Yes",0,1),IF(D14="Yes",1,0)))*IF(D14="N/A",0,'Scoring Model'!$F14) -> 0 | J14: =IF(E14="N/A",0,IF('Scoring Model'!$E14="Positive",IF(E14="Yes",0,1),IF(E14="Yes",1,0)))*IF(E14="N/A",0,'Scoring Model'!$F14) -> 0 | K14: =IF(F14="N/A",0,IF('Scoring Model'!$E14="Positive",IF(F14="Yes",0,1),IF(F14="Yes",1,0)))*IF(F14="N/A",0,'Scoring Model'!$F14) -> 9 | L14: =IF(G14="N/A",0,IF('Scoring Model'!$E14="Positive",IF(G14="Yes",0,1),IF(G14="Yes",1,0)))*IF(G14="N/A",0,'Scoring Model'!$F14) -> 0 | M14: =IF(C14="N/A",0,'Scoring Model'!$F14) -> 9 | N14: =IF(D14="N/A",0,'Scoring Model'!$F14) -> 9 | O14: =IF(E14="N/A",0,'Scoring Model'!$F14) -> 9 | P14: =IF(F14="N/A",0,'Scoring Model'!$F14) -> 9 | Q14: =IF(G14="N/A",0,'Scoring Model'!$F14) -> 9
A15: T1 | B15: ='Scoring Model'!F15 -> 5 | C15: No | D15: Yes | E15: No | F15: Yes | G15: No | H15: =IF(C15="N/A",0,IF('Scoring Model'!$E15="Positive",IF(C15="Yes",0,1),IF(C15="Yes",1,0)))*IF(C15="N/A",0,'Scoring Model'!$F15) -> 5 | I15: =IF(D15="N/A",0,IF('Scoring Model'!$E15="Positive",IF(D15="Yes",0,1),IF(D15="Yes",1,0)))*IF(D15="N/A",0,'Scoring Model'!$F15) -> 0 | J15: =IF(E15="N/A",0,IF('Scoring Model'!$E15="Positive",IF(E15="Yes",0,1),IF(E15="Yes",1,0)))*IF(E15="N/A",0,'Scoring Model'!$F15) -> 5 | K15: =IF(F15="N/A",0,IF('Scoring Model'!$E15="Positive",IF(F15="Yes",0,1),IF(F15="Yes",1,0)))*IF(F15="N/A",0,'Scoring Model'!$F15) -> 0 | L15: =IF(G15="N/A",0,IF('Scoring Model'!$E15="Positive",IF(G15="Yes",0,1),IF(G15="Yes",1,0)))*IF(G15="N/A",0,'Scoring Model'!$F15) -> 5 | M15: =IF(C15="N/A",0,'Scoring Model'!$F15) -> 5 | N15: =IF(D15="N/A",0,'Scoring Model'!$F15) -> 5 | O15: =IF(E15="N/A",0,'Scoring Model'!$F15) -> 5 | P15: =IF(F15="N/A",0,'Scoring Model'!$F15) -> 5 | Q15: =IF(G15="N/A",0,'Scoring Model'!$F15) -> 5
A16: T2 | B16: ='Scoring Model'!F16 -> 3 | C16: N/A | D16: Yes | E16: N/A | F16: Yes | G16: N/A | H16: =IF(C16="N/A",0,IF('Scoring Model'!$E16="Positive",IF(C16="Yes",0,1),IF(C16="Yes",1,0)))*IF(C16="N/A",0,'Scoring Model'!$F16) -> 0 | I16: =IF(D16="N/A",0,IF('Scoring Model'!$E16="Positive",IF(D16="Yes",0,1),IF(D16="Yes",1,0)))*IF(D16="N/A",0,'Scoring Model'!$F16) -> 0 | J16: =IF(E16="N/A",0,IF('Scoring Model'!$E16="Positive",IF(E16="Yes",0,1),IF(E16="Yes",1,0)))*IF(E16="N/A",0,'Scoring Model'!$F16) -> 0 | K16: =IF(F16="N/A",0,IF('Scoring Model'!$E16="Positive",IF(F16="Yes",0,1),IF(F16="Yes",1,0)))*IF(F16="N/A",0,'Scoring Model'!$F16) -> 0 | L16: =IF(G16="N/A",0,IF('Scoring Model'!$E16="Positive",IF(G16="Yes",0,1),IF(G16="Yes",1,0)))*IF(G16="N/A",0,'Scoring Model'!$F16) -> 0 | M16: =IF(C16="N/A",0,'Scoring Model'!$F16) -> 0 | N16: =IF(D16="N/A",0,'Scoring Model'!$F16) -> 3 | O16: =IF(E16="N/A",0,'Scoring Model'!$F16) -> 0 | P16: =IF(F16="N/A",0,'Scoring Model'!$F16) -> 3 | Q16: =IF(G16="N/A",0,'Scoring Model'!$F16) -> 0
... A19: CS4 | B19: ='Scoring Model'!F19 -> 6 | C19: Yes | D19: Yes | E19: Yes | F19: Yes | G19: Yes | H19: =IF(C19="N/A",0,IF('Scoring Model'!$E19="Positive",IF(C19="Yes",0,1),IF(C19="Yes",1,0)))*IF(C19="N/A",0,'Scoring Model'!$F19) -> 0 | I19: =IF(D19="N/A",0,IF('Scoring Model'!$E19="Positive",IF(D19="Yes",0,1),IF(D19="Yes",1,0)))*IF(D19="N/A",0,'Scoring Model'!$F19) -> 0 | J19: =IF(E19="N/A",0,IF('Scoring Model'!$E19="Positive",IF(E19="Yes",0,1),IF(E19="Yes",1,0)))*IF(E19="N/A",0,'Scoring Model'!$F19) -> 0 | K19: =IF(F19="N/A",0,IF('Scoring Model'!$E19="Positive",IF(F19="Yes",0,1),IF(F19="Yes",1,0)))*IF(F19="N/A",0,'Scoring Model'!$F19) -> 0 | L19: =IF(G19="N/A",0,IF('Scoring Model'!$E19="Positive",IF(G19="Yes",0,1),IF(G19="Yes",1,0)))*IF(G19="N/A",0,'Scoring Model'!$F19) -> 0 | M19: =IF(C19="N/A",0,'Scoring Model'!$F19) -> 6 | N19: =IF(D19="N/A",0,'Scoring Model'!$F19) -> 6 | O19: =IF(E19="N/A",0,'Scoring Model'!$F19) -> 6 | P19: =IF(F19="N/A",0,'Scoring Model'!$F19) -> 6 | Q19: =IF(G19="N/A",0,'Scoring Model'!$F19) -> 6
A20: Total weighted risk | C20: =SUM(H5:H19) -> 10 | D20: =SUM(I5:I19) -> 7.5 | E20: =SUM(J5:J19) -> 31.5 | F20: =SUM(K5:K19) -> 53 | G20: =SUM(L5:L19) -> 15.5
A21: Total applicable weight | C21: =SUM(M5:M19) -> 97 | D21: =SUM(N5:N19) -> 100 | E21: =SUM(O5:O19) -> 97 | F21: =SUM(P5:P19) -> 100 | G21: =SUM(Q5:Q19) -> 97
A22: Normalised risk score | C22: =IFERROR(C20/C21,0) -> 0.10309278 | D22: =IFERROR(D20/D21,0) -> 0.075 | E22: =IFERROR(E20/E21,0) -> 0.32474227 | F22: =IFERROR(F20/F21,0) -> 0.53 | G22: =IFERROR(G20/G21,0) -> 0.15979381
A23: Risk score (0–100) | C23: =C22*100 -> 10.309278 | D23: =D22*100 -> 7.5 | E23: =E22*100 -> 32.474227 | F23: =F22*100 -> 53 | G23: =G22*100 -> 15.979381
A24: Risk band | C24: =INDEX(Bands!$B$4:$B$7,MATCH(C22,Bands!$A$4:$A$7,1)) -> Moderate | D24: =INDEX(Bands!$B$4:$B$7,MATCH(D22,Bands!$A$4:$A$7,1)) -> Low | E24: =INDEX(Bands!$B$4:$B$7,MATCH(E22,Bands!$A$4:$A$7,1)) -> Elevated | F24: =INDEX(Bands!$B$4:$B$7,MATCH(F22,Bands!$A$4:$A$7,1)) -> High | G24: =INDEX(Bands!$B$4:$B$7,MATCH(G22,Bands!$A$4:$A$7,1)) -> Moderate
A25: Knockout triggered | C25: =IF(SUMPRODUCT(('Scoring Model'!$K$5:$K$19=1)*(H5:H19>0))>0,"Yes","No") -> No | D25: =IF(SUMPRODUCT(('Scoring Model'!$K$5:$K$19=1)*(I5:I19>0))>0,"Yes","No") -> No | E25: =IF(SUMPRODUCT(('Scoring Model'!$K$5:$K$19=1)*(J5:J19>0))>0,"Yes","No") -> No | F25: =IF(SUMPRODUCT(('Scoring Model'!$K$5:$K$19=1)*(K5:K19>0))>0,"Yes","No") -> Yes | G25: =IF(SUMPRODUCT(('Scoring Model'!$K$5:$K$19=1)*(L5:L19>0))>0,"Yes","No") -> No
A26: Recommendation | C26: =IF(C25="Yes","Refer to committee — knockout",INDEX(Bands!$C$4:$C$7,MATCH(C22,Bands!$A$4:$A$7,1))) -> Approve with conditions or monitoring | D26: =IF(D25="Yes","Refer to committee — knockout",INDEX(Bands!$C$4:$C$7,MATCH(D22,Bands!$A$4:$A$7,1))) -> Recommend approval | E26: =IF(E25="Yes","Refer to committee — knockout",INDEX(Bands!$C$4:$C$7,MATCH(E22,Bands!$A$4:$A$7,1))) -> Refer for supervisory review | F26: =IF(F25="Yes","Refer to committee — knockout",INDEX(Bands!$C$4:$C$7,MATCH(F22,Bands!$A$4:$A$7,1))) -> Refer to committee — knockout | G26: =IF(G25="Yes","Refer to committee — knockout",INDEX(Bands!$C$4:$C$7,MATCH(G22,Bands!$A$4:$A$7,1))) -> Approve with conditions or monitoring
A29: Answers corrected by authentication before scoring
A30: Application | B30: QID | C30: Submitted | D30: Scored | E30: Why
A31: APP003 | B31: Q3 | C31: Yes | D31: No | E31: Employment letter supports 8 years 2 months, not ten.
A32: APP003 | B32: PC19 | C32: No | D32: Yes | E32: Tax certificate records a 2019/2020 filing 231 days late, penalty levied.
A33: APP004 | B33: PC1 | C33: No | D33: Yes | E33: Police clearance records a 2013 conviction under s.34 Companies Act.
A35: What the corrections change (illustrative — the engine never scores the uncorrected answers)
A36: Application | B36: Score if uncorrected | C36: Band if uncorrected | D36: Knockout if uncorrected | E36: Score as scored | F36: Band as scored | G36: Knockout as scored
A37: APP003 | B37: =(E20-J8-J10)/E21*100 -> 11.85567 | C37: =INDEX(Bands!$B$4:$B$7,MATCH(B37/100,Bands!$A$4:$A$7,1)) -> Moderate | D37: No | E37: =E23 -> 32.474227 | F37: =E24 -> Elevated | G37: =E25 -> No
A38: APP004 | B38: =(F20-K9)/F21*100 -> 35 | C38: =INDEX(Bands!$B$4:$B$7,MATCH(B38/100,Bands!$A$4:$A$7,1)) -> Elevated | D38: No | E38: =F23 -> 53 | F38: =F24 -> High | G38: =F25 -> Yes
A40: Open decision: T1 for non-executive appointments
A41: T1 is Positive, so a non-executive correctly answering No is charged its full weight — the same effect T2 had before it was made N/A. The rows below show each applicant's score if T1 were N/A for non-executive appointments. Not applied to the scores above.
A42: Non-executive appointment | C42: =IF(C16="N/A","Yes","No") -> Yes | D42: =IF(D16="N/A","Yes","No") -> No | E42: =IF(E16="N/A","Yes","No") -> Yes | F42: =IF(F16="N/A","Yes","No") -> No | G42: =IF(G16="N/A","Yes","No") -> Yes
A43: Weighted risk with T1 N/A | C43: =C20-IF(C42="Yes",H15,0) -> 5 | D43: =D20-IF(D42="Yes",I15,0) -> 7.5 | E43: =E20-IF(E42="Yes",J15,0) -> 26.5 | F43: =F20-IF(F42="Yes",K15,0) -> 53 | G43: =G20-IF(G42="Yes",L15,0) -> 10.5
A44: Applicable weight with T1 N/A | C44: =C21-IF(C42="Yes",M15,0) -> 92 | D44: =D21-IF(D42="Yes",N15,0) -> 100 | E44: =E21-IF(E42="Yes",O15,0) -> 92 | F44: =F21-IF(F42="Yes",P15,0) -> 100 | G44: =G21-IF(G42="Yes",Q15,0) -> 92
A45: Risk score with T1 N/A | C45: =IFERROR(C43/C44,0)*100 -> 5.4347826 | D45: =IFERROR(D43/D44,0)*100 -> 7.5 | E45: =IFERROR(E43/E44,0)*100 -> 28.804348 | F45: =IFERROR(F43/F44,0)*100 -> 53 | G45: =IFERROR(G43/G44,0)*100 -> 11.413043
A46: Risk band with T1 N/A | C46: =INDEX(Bands!$B$4:$B$7,MATCH(C45/100,Bands!$A$4:$A$7,1)) -> Low | D46: =INDEX(Bands!$B$4:$B$7,MATCH(D45/100,Bands!$A$4:$A$7,1)) -> Low | E46: =INDEX(Bands!$B$4:$B$7,MATCH(E45/100,Bands!$A$4:$A$7,1)) -> Elevated | F46: =INDEX(Bands!$B$4:$B$7,MATCH(F45/100,Bands!$A$4:$A$7,1)) -> High | G46: =INDEX(Bands!$B$4:$B$7,MATCH(G45/100,Bands!$A$4:$A$7,1)) -> Moderate
A47: Change in score | C47: =C45-C23 -> -4.8744957 | D47: =D45-D23 -> 0 | E47: =E45-E23 -> -3.669879 | F47: =F45-F23 -> 0 | G47: =G45-G23 -> -4.566338

Sheet Change Log
A1: Changes since the previous scoring model (fnp_scoring_model_15q.xlsx)
A3: Change | B3: Detail | C3: Effect on scores
A4: A4 polarity: Positive → Negative | B4: Naturalised (Yes) now contributes the question weight of 1.5. | C4: Only APP003 (the one naturalised applicant): +1.5 risk.
A5: Section renamed: Age → Basic Details | B5: Label only; weight (4) and questions (A1, A4) unchanged. | C5: None.
A6: Knock-out → knockout, Yes/No → 1/0 | B6: Matches the engine input JSON. PC1 remains the single knockout. | C6: None.
A7: Question wording | B7: PC1 no longer names a country; FC7 threshold reads N$2.5mn; CoI6 defines a controlling interest as 20% or more of voting shares, or the ability to appoint or remove a majority of the board. | C7: None — wording only.
A8: Generated from the applicant JSON | B8: Weights, polarity, knockout flags and question text are read from APP001.json rather than retyped, so the model and the engine input cannot silently disagree at build time. | C8: None.
A9: Worked examples score post-correction answers | B9: APP003 (Q3, PC19) and APP004 (PC1) are scored on the corrected answers, since the engine only ever receives those. A table shows what the uncorrected answers would have scored. | C9: APP004 moves from Elevated with no knockout to High with the knockout triggered.
A10: Reconciled to the backend engine | B10: APP001: total weighted risk 10.0 over applicable weight 97.0 gives 10.309278, band Moderate, no knockout — identical to the engine's score_summary. | C10: —
A12: Not changed, but open
A13: T1 (Positive) charges a non-executive for correctly answering No — see Worked Examples. Weights, section weights, bands and the knockout rule are unchanged.

Sheet Notes and Assumptions
A1: Design notes and assumptions
A3: How the score works
A4: Each question carries a weight in risk points. An unfavourable answer contributes its full weight; a favourable answer contributes nothing. The normalised score is total weighted risk divided by total applicable weight, so it lands between 0 and 1 regardless of how many questions are N/A. Lower is better.
A8: Weights follow severity, not question count
A9: Section weights sum to 100 and are set by consequence. Within a section the split is deliberately uneven: Q3 carries twice Q1, PC1 more than twice PC19.
A13: The knockout sits outside the weighted score
A14: A conviction alone contributes 18 of 100, which reads as Moderate. That is the wrong outcome, so PC1 is a knockout: a risk flag on it refers the case whatever the total.
A18: Answers are taken as true
A19: Scoring runs only after every answer has been authenticated against its evidence. Mismatches go back to the filer first, so the model carries no evidence-state column and no confidence discount.
A23: N/A handling
A24: N/A removes a question from both numerator and denominator. T2 is the live case: for a non-executive appointment it is N/A rather than No. N/A is a property of the appointment type, set when the form is built.
A28: Polarity notes
... A44: Two references in the question text are still tied to the source instrument: PC19 cites “Section 3(1)(iii) of the Act” and CoI2 says “as defined in the BSA”. Both need replacing with the equivalent Namibian provisions.
